__tests_old/__init__.py
__tests_old/__main__.py
__tests_old/conftest.py
__tests_old/data.py
__tests_old/integration/__init__.py
__tests_old/integration/test_ac_noise_analysis.py
__tests_old/integration/test_ac_signal_analysis.py
__tests_old/integration/test_data_function_operators.py
__tests_old/integration/test_mutual_inductance.py
__tests_old/integration/test_solution.py
__tests_old/integration/liso/__init__.py
__tests_old/integration/liso/test_input_parser.py
__tests_old/integration/liso/test_output_parser.py
__tests_old/unit/__init__.py
__tests_old/unit/test_circuit.py
__tests_old/unit/test_component.py
__tests_old/unit/test_config_components.py
__tests_old/unit/test_data.py
__tests_old/unit/test_format.py
__tests_old/unit/test_input.py
__tests_old/unit/test_library.py
__tests_old/unit/test_solution.py
__tests_old/unit/liso/__init__.py
__tests_old/unit/liso/test_input.py
__tests_old/validation/__init__.py
__tests_old/validation/liso.py
__zero_old/__init__.py
__zero_old/__main__.py
__zero_old/_version.py
__zero_old/circuit.py
__zero_old/components copy.py
__zero_old/components.py
__zero_old/data.py
__zero_old/display.py
__zero_old/format.py
__zero_old/misc.py
__zero_old/noise.py
__zero_old/solution.py
__zero_old/tools.py
__zero_old/analysis/__init__.py
__zero_old/analysis/base.py
__zero_old/analysis/ac/__init__.py
__zero_old/analysis/ac/base.py
__zero_old/analysis/ac/noise.py
__zero_old/analysis/ac/signal.py
__zero_old/config/__init__.py
__zero_old/config/base.py
__zero_old/config/components.py
__zero_old/config/query.py
__zero_old/config/settings.py
__zero_old/datasheet/__init__.py
__zero_old/datasheet/fetch.py
__zero_old/datasheet/parts.py
__zero_old/liso/__init__.py
__zero_old/liso/base.py
__zero_old/liso/input.py
__zero_old/liso/output.py
__zero_old/liso/runner.py
__zero_old/solve/__init__.py
__zero_old/solve/base.py
__zero_old/solve/scipy.py
tests/__init__.py
tests/__main__.py
tests/data.py
tests/integration/__init__.py
zero-0.9.2.dist-info/LICENSE
zero-0.9.2.dist-info/METADATA
zero-0.9.2.dist-info/WHEEL
zero-0.9.2.dist-info/entry_points.txt
zero-0.9.2.dist-info/top_level.txt
zero-0.9.2.dist-info/RECORD
