Metadata-Version: 2.1
Name: zero
Version: 0.9.2
Summary: Linear circuit simulator
Home-page: https://git.ligo.org/sean-leavey/zero
Author: Sean Leavey
Author-email: sean.leavey@ligo.org
License: GPLv3
Classifier: Intended Audience :: Science/Research
Classifier: License :: OSI Approved :: GNU General Public License v3 (GPLv3)
Classifier: Natural Language :: English
Classifier: Programming Language :: Python :: 3
Classifier: Programming Language :: Python :: 3.6
Classifier: Programming Language :: Python :: 3.7
Classifier: Programming Language :: Python :: 3.8
License-File: LICENSE
Requires-Dist: numpy >=1.15.2
Requires-Dist: scipy >=1.1.0
Requires-Dist: matplotlib >=3.0.3
Requires-Dist: requests >=2.19.1
Requires-Dist: progressbar2 >=3.38.0
Requires-Dist: tabulate >=0.8.2
Requires-Dist: setuptools-scm >=3.1.0
Requires-Dist: ply >=3.11
Requires-Dist: Click ==7.0
Requires-Dist: quantiphy >=2.5.0
Requires-Dist: PyYAML >=3.13
Requires-Dist: graphviz >=0.9
Provides-Extra: dev
Requires-Dist: pylint ; extra == 'dev'
Requires-Dist: bandit ; extra == 'dev'
Requires-Dist: sphinx ; extra == 'dev'
Requires-Dist: sphinx-autobuild ; extra == 'dev'
Requires-Dist: sphinx-click ; extra == 'dev'
Requires-Dist: sphinx-rtd-theme ; extra == 'dev'
Requires-Dist: sphinxcontrib-programoutput ; extra == 'dev'
Requires-Dist: doc8 ; extra == 'dev'
Requires-Dist: numpydoc ; extra == 'dev'
Requires-Dist: nbsphinx ; extra == 'dev'
